{
  "ALTER-SESSION-13.sql": [
    5
  ],
  "ALTER-TABLE-102.sql": [
    2,
    5
  ],
  "ALTER-TABLE-19.sql": [
    4,
    5,
    6,
    7,
    8
  ],
  "ALTER-TABLE-79.sql": [
    5,
    6,
    7
  ],
  "COLLATION-0.sql": [
    6
  ],
  "COMMIT-0.sql": [
    2
  ],
  "CREATE-TABLE-40.sql": [
    2
  ],
  "CURRENT_TIMESTAMP-2.sql": [
    2
  ],
  "CURRENT_TIMESTAMP-3.sql": [
    2
  ],
  "Comments-46.sql": [
    3
  ],
  "DEREF-0.sql": [
    2,
    5
  ],
  "Data-Types-3.sql": [
    4,
    5,
    6,
    7
  ],
  "HEXTORAW-0.sql": [
    4
  ],
  "INSERT-0.sql": [
    2
  ],
  "INSERT-1.sql": [
    2
  ],
  "INSERT-10.sql": [
    2,
    3,
    4
  ],
  "INSERT-11.sql": [
    2,
    4,
    6
  ],
  "INSERT-14.sql": [
    2
  ],
  "INSERT-27.sql": [
    2
  ],
  "INSERT-28.sql": [
    2
  ],
  "INSERT-3.sql": [
    2
  ],
  "INSERT-4.sql": [
    2
  ],
  "INSERT-6.sql": [
    2
  ],
  "INSERT-7.sql": [
    2
  ],
  "INSERT-8.sql": [
    2
  ],
  "JSON_TABLE-1.sql": [
    2
  ],
  "LOCALTIMESTAMP-2.sql": [
    2
  ],
  "LOCALTIMESTAMP-3.sql": [
    2
  ],
  "Literals-15.sql": [
    2,
    3
  ],
  "Literals-18.sql": [
    2
  ],
  "Literals-19.sql": [
    2
  ],
  "Literals-20.sql": [
    2
  ],
  "NANVL-0.sql": [
    2
  ],
  "NLSSORT-1.sql": [
    3,
    4,
    5
  ],
  "Pattern-matching-Conditions-10.sql": [
    3
  ],
  "SELECT-52.sql": [
    2
  ],
  "SELECT-69.sql": [
    6,
    7,
    8,
    9
  ],
  "SELECT-78.sql": [
    2
  ],
  "SELECT-93.sql": [
    4,
    5,
    6,
    7,
    8,
    9,
    10,
    11,
    12,
    13,
    14,
    15,
    16,
    17,
    18,
    19,
    20,
    21,
    22,
    23
  ],
  "SQL-JSON-Conditions-1.sql": [
    2,
    3,
    4,
    5,
    6,
    7,
    8
  ],
  "SQL-JSON-Conditions-15.sql": [
    2,
    3,
    4,
    5,
    6,
    7
  ],
  "SQL-JSON-Conditions-22.sql": [
    2,
    5,
    8
  ],
  "SQL-JSON-Conditions-6.sql": [
    2,
    3,
    4
  ],
  "Sequence-Pseudocolumns-4.sql": [
    2
  ],
  "Syntax-for-Schema-Objects-and-Parts-in-SQL-Statements-0.sql": [
    2
  ],
  "TO_BINARY_DOUBLE-0.sql": [
    5
  ],
  "TO_CHAR-datetime-2.sql": [
    3,
    7
  ],
  "TRANSLATE-USING-0.sql": [
    4
  ],
  "Type-Constructor-Expressions-0.sql": [
    8
  ],
  "Using-XML-in-SQL-Statements-1.sql": [
    2
  ]
}